link/__init__.py
link/feature/__init__.py
link/feature/core.py
link/feature/test/__init__.py
link/feature/test/core.py
link.feature-2.1.dist-info/DESCRIPTION.rst
link.feature-2.1.dist-info/METADATA
link.feature-2.1.dist-info/RECORD
link.feature-2.1.dist-info/WHEEL
link.feature-2.1.dist-info/metadata.json
link.feature-2.1.dist-info/top_level.txt
